{
"sid": "tutorial",
"mainIconSid": "main_icon",
"hubIconSid": "save_icon",

"transferHeroProgressFromSession": false,
"showReputationPanel": false,
"showHeroPanel": false,

"firstShowActions": 
[
    { "type":       "OpenGuide",
    "values":     [ "tutorial_intro" ] }
],

"nodes": 
    [
        {
            "sid": "Tutorial_Node_0",
            "state": "Activated",

            "repeatable": true,
            "importanceType": "Main",

            "posX": -100.0, "posY": -50.0, "posZ": 0.0,

            "interactionActions": 
            [
                { "type":       "OpenMissionsPrologue",
                "values":     [ "Tutorial_Mission_0" ] }
            ],

            "onDoneActions": 
            [
                { "type":       "SetCounterValue",
                "values":     [ "Tutorial_Mission_1_Completed", "1" ] },

                { "type":       "ChangeCompletedNodeTooltip",
                "values":     [ "Tutorial_Node_0", "Mission_Complete", "Vi_Zavershili_Tutorial_0" ] },

                { "type":       "OpenDialog",
                  "values":     [ "t_M_post_mission_basic" ] },

                { "type":       "changeNodeState",
                "values":     [ "Tutorial_Node_1", "Activated" ] },

                { "type":       "InteractWithNode",
                "values":     [ "Tutorial_Node_1" ] }
            ]
        },

        {
            "sid": "Tutorial_Node_1",
            "state": "Hidden",

            "repeatable": true,
            "importanceType": "Main",

            "posX": -100.0, "posY": 50.0, "posZ": 0.0,

            "interactionActions": 
            [
                { "type":       "OpenMissionsPrologue",
                "values":     [ "Tutorial_Mission_1" ] }
            ],

            "onDoneActions": 
            [
                { "type":       "ChangeCompletedNodeTooltip",
                "values":     [ "Tutorial_Node_1", "Mission_Complete", "Vi_Zavershili_Tutorial_1" ] },

                { "type":       "OpenDialog",
                  "values":     [ "t_M_post_mission" ] },

                  { "type":       "changeNodeState",
                  "values":     [ "Tutorial_Challenge_None_1", "Activated" ] },
                  { "type":       "changeNodeState",
                  "values":     [ "Tutorial_Challenge_None_2", "Activated" ] },
                  { "type":       "changeNodeState",
                  "values":     [ "Tutorial_Challenge_None_3", "Activated" ] },
                  { "type":       "changeNodeState",
                  "values":     [ "Tutorial_Challenge_None_4", "Activated" ] },
                  { "type":       "changeNodeState",
                  "values":     [ "Tutorial_Challenge_None_5", "Activated" ] },
                  { "type":       "changeNodeState",
                  "values":     [ "Tutorial_Challenge_None_6", "Activated" ] },
                  { "type":       "changeNodeState",
                  "values":     [ "Tutorial_Challenge_None_7", "Activated" ] },
                  { "type":       "changeNodeState",
                  "values":     [ "Tutorial_Challenge_None_8", "Activated" ] },

                  { "type":       "SetAchievement",
                    "values":     [ "achievement_1" ] }
            ]
        },

        {
            "sid": "Tutorial_Challenge_None_1",
            "state": "Hidden",

            "repeatable": true,
            "importanceType": "Side",

            "posX": 100.0, "posY": -125.0, "posZ": 0.0,

            "interactionActions": 
            [
                { "type":       "OpenMissionsPrologue",
                "values":     [ "Tutorial_Challenge_Mission_1" ] }
            ],

            "onDoneActions": 
            [
                { "type":       "SetCounterValue",
                "values":     [ "Tutorial_Challenge_Mission_1_Completed", "1" ] },

                { "type":       "SetAchievement",
                  "conditions": { "logicOperation": "And", "array": [ 
                                { "counterSid": "Tutorial_Challenge_Mission_1_Completed", "operation": "==", "value": 1 },
                                { "counterSid": "Tutorial_Challenge_Mission_2_Completed", "operation": "==", "value": 1 },
                                { "counterSid": "Tutorial_Challenge_Mission_3_Completed", "operation": "==", "value": 1 },
                                { "counterSid": "Tutorial_Challenge_Mission_4_Completed", "operation": "==", "value": 1 },
                                { "counterSid": "Tutorial_Challenge_Mission_5_Completed", "operation": "==", "value": 1 },
                                { "counterSid": "Tutorial_Challenge_Mission_6_Completed", "operation": "==", "value": 1 },
                                { "counterSid": "Tutorial_Challenge_Mission_7_Completed", "operation": "==", "value": 1 },
                                { "counterSid": "Tutorial_Challenge_Mission_8_Completed", "operation": "==", "value": 1 }
                                                                    ] },
                  "values":     [ "achievement_2" ] }
            ]
        },

        {
            "sid": "Tutorial_Challenge_None_2",
            "state": "Hidden",

            "repeatable": true,
            "importanceType": "Side",

            "posX": -200.0, "posY": 100.0, "posZ": 0.0,

            "interactionActions": 
            [
                { "type":       "OpenMissionsPrologue",
                "values":     [ "Tutorial_Challenge_Mission_2" ] }
            ],

            "onDoneActions": 
            [
                { "type":       "SetCounterValue",
                "values":     [ "Tutorial_Challenge_Mission_2_Completed", "1" ] },

                { "type":       "SetAchievement",
                  "conditions": { "logicOperation": "And", "array": [ 
                                { "counterSid": "Tutorial_Challenge_Mission_1_Completed", "operation": "==", "value": 1 },
                                { "counterSid": "Tutorial_Challenge_Mission_2_Completed", "operation": "==", "value": 1 },
                                { "counterSid": "Tutorial_Challenge_Mission_3_Completed", "operation": "==", "value": 1 },
                                { "counterSid": "Tutorial_Challenge_Mission_4_Completed", "operation": "==", "value": 1 },
                                { "counterSid": "Tutorial_Challenge_Mission_5_Completed", "operation": "==", "value": 1 },
                                { "counterSid": "Tutorial_Challenge_Mission_6_Completed", "operation": "==", "value": 1 },
                                { "counterSid": "Tutorial_Challenge_Mission_7_Completed", "operation": "==", "value": 1 },
                                { "counterSid": "Tutorial_Challenge_Mission_8_Completed", "operation": "==", "value": 1 }
                                                                    ] },
                  "values":     [ "achievement_2" ] }
            ]
        },

        {
            "sid": "Tutorial_Challenge_None_3",
            "state": "Hidden",

            "repeatable": true,
            "importanceType": "Side",

            "posX": 200.0, "posY": 25.0, "posZ": 0.0,

            "interactionActions": 
            [
                { "type":       "OpenMissionsPrologue",
                "values":     [ "Tutorial_Challenge_Mission_3" ] }
            ],

            "onDoneActions": 
            [
                { "type":       "SetCounterValue",
                "values":     [ "Tutorial_Challenge_Mission_3_Completed", "1" ] },

                { "type":       "SetAchievement",
                  "conditions": { "logicOperation": "And", "array": [ 
                                { "counterSid": "Tutorial_Challenge_Mission_1_Completed", "operation": "==", "value": 1 },
                                { "counterSid": "Tutorial_Challenge_Mission_2_Completed", "operation": "==", "value": 1 },
                                { "counterSid": "Tutorial_Challenge_Mission_3_Completed", "operation": "==", "value": 1 },
                                { "counterSid": "Tutorial_Challenge_Mission_4_Completed", "operation": "==", "value": 1 },
                                { "counterSid": "Tutorial_Challenge_Mission_5_Completed", "operation": "==", "value": 1 },
                                { "counterSid": "Tutorial_Challenge_Mission_6_Completed", "operation": "==", "value": 1 },
                                { "counterSid": "Tutorial_Challenge_Mission_7_Completed", "operation": "==", "value": 1 },
                                { "counterSid": "Tutorial_Challenge_Mission_8_Completed", "operation": "==", "value": 1 }
                                                                    ] },
                  "values":     [ "achievement_2" ] }
            ]
        },

        {
            "sid": "Tutorial_Challenge_None_4",
            "state": "Hidden",

            "repeatable": true,
            "importanceType": "Side",

            "posX": -550.0, "posY": -50.0, "posZ": 0.0,

            "interactionActions": 
            [
                { "type":       "OpenMissionsPrologue",
                "values":     [ "Tutorial_Challenge_Mission_4" ] }
            ],

            "onDoneActions": 
            [
                { "type":       "SetCounterValue",
                "values":     [ "Tutorial_Challenge_Mission_4_Completed", "1" ] },

                { "type":       "SetAchievement",
                  "conditions": { "logicOperation": "And", "array": [ 
                                { "counterSid": "Tutorial_Challenge_Mission_1_Completed", "operation": "==", "value": 1 },
                                { "counterSid": "Tutorial_Challenge_Mission_2_Completed", "operation": "==", "value": 1 },
                                { "counterSid": "Tutorial_Challenge_Mission_3_Completed", "operation": "==", "value": 1 },
                                { "counterSid": "Tutorial_Challenge_Mission_4_Completed", "operation": "==", "value": 1 },
                                { "counterSid": "Tutorial_Challenge_Mission_5_Completed", "operation": "==", "value": 1 },
                                { "counterSid": "Tutorial_Challenge_Mission_6_Completed", "operation": "==", "value": 1 },
                                { "counterSid": "Tutorial_Challenge_Mission_7_Completed", "operation": "==", "value": 1 },
                                { "counterSid": "Tutorial_Challenge_Mission_8_Completed", "operation": "==", "value": 1 }
                                                                    ] },
                  "values":     [ "achievement_2" ] }
            ]
        },

        {
            "sid": "Tutorial_Challenge_None_5",
            "state": "Hidden",

            "repeatable": true,
            "importanceType": "Side",

            "posX": -650.0, "posY": 50.0, "posZ": 0.0,

            "interactionActions": 
            [
                { "type":       "OpenMissionsPrologue",
                "values":     [ "Tutorial_Challenge_Mission_5" ] }
            ],

            "onDoneActions": 
            [
                { "type":       "SetCounterValue",
                "values":     [ "Tutorial_Challenge_Mission_5_Completed", "1" ] },

                { "type":       "SetAchievement",
                  "conditions": { "logicOperation": "And", "array": [ 
                                { "counterSid": "Tutorial_Challenge_Mission_1_Completed", "operation": "==", "value": 1 },
                                { "counterSid": "Tutorial_Challenge_Mission_2_Completed", "operation": "==", "value": 1 },
                                { "counterSid": "Tutorial_Challenge_Mission_3_Completed", "operation": "==", "value": 1 },
                                { "counterSid": "Tutorial_Challenge_Mission_4_Completed", "operation": "==", "value": 1 },
                                { "counterSid": "Tutorial_Challenge_Mission_5_Completed", "operation": "==", "value": 1 },
                                { "counterSid": "Tutorial_Challenge_Mission_6_Completed", "operation": "==", "value": 1 },
                                { "counterSid": "Tutorial_Challenge_Mission_7_Completed", "operation": "==", "value": 1 },
                                { "counterSid": "Tutorial_Challenge_Mission_8_Completed", "operation": "==", "value": 1 }
                                                                    ] },
                  "values":     [ "achievement_2" ] }
            ]
        },

        {
            "sid": "Tutorial_Challenge_None_6",
            "state": "Hidden",

            "repeatable": true,
            "importanceType": "Side",

            "posX": -275.0, "posY": -40.0, "posZ": 0.0,

            "interactionActions": 
            [
                { "type":       "OpenMissionsPrologue",
                "values":     [ "Tutorial_Challenge_Mission_6" ] }
            ],

            "onDoneActions": 
            [
                { "type":       "SetCounterValue",
                "values":     [ "Tutorial_Challenge_Mission_6_Completed", "1" ] },

                { "type":       "SetAchievement",
                  "conditions": { "logicOperation": "And", "array": [ 
                                { "counterSid": "Tutorial_Challenge_Mission_1_Completed", "operation": "==", "value": 1 },
                                { "counterSid": "Tutorial_Challenge_Mission_2_Completed", "operation": "==", "value": 1 },
                                { "counterSid": "Tutorial_Challenge_Mission_3_Completed", "operation": "==", "value": 1 },
                                { "counterSid": "Tutorial_Challenge_Mission_4_Completed", "operation": "==", "value": 1 },
                                { "counterSid": "Tutorial_Challenge_Mission_5_Completed", "operation": "==", "value": 1 },
                                { "counterSid": "Tutorial_Challenge_Mission_6_Completed", "operation": "==", "value": 1 },
                                { "counterSid": "Tutorial_Challenge_Mission_7_Completed", "operation": "==", "value": 1 },
                                { "counterSid": "Tutorial_Challenge_Mission_8_Completed", "operation": "==", "value": 1 }
                                                                    ] },
                  "values":     [ "achievement_2" ] }
            ]
        },

        {
            "sid": "Tutorial_Challenge_None_7",
            "state": "Hidden",

            "repeatable": true,
            "importanceType": "Side",

            "posX": 80.0, "posY": 300.0, "posZ": 0.0,

            "interactionActions": 
            [
                { "type":       "OpenMissionsPrologue",
                "values":     [ "Tutorial_Challenge_Mission_7" ] }
            ],

            "onDoneActions": 
            [
                { "type":       "SetCounterValue",
                "values":     [ "Tutorial_Challenge_Mission_7_Completed", "1" ] },

                { "type":       "SetAchievement",
                  "conditions": { "logicOperation": "And", "array": [ 
                                { "counterSid": "Tutorial_Challenge_Mission_1_Completed", "operation": "==", "value": 1 },
                                { "counterSid": "Tutorial_Challenge_Mission_2_Completed", "operation": "==", "value": 1 },
                                { "counterSid": "Tutorial_Challenge_Mission_3_Completed", "operation": "==", "value": 1 },
                                { "counterSid": "Tutorial_Challenge_Mission_4_Completed", "operation": "==", "value": 1 },
                                { "counterSid": "Tutorial_Challenge_Mission_5_Completed", "operation": "==", "value": 1 },
                                { "counterSid": "Tutorial_Challenge_Mission_6_Completed", "operation": "==", "value": 1 },
                                { "counterSid": "Tutorial_Challenge_Mission_7_Completed", "operation": "==", "value": 1 },
                                { "counterSid": "Tutorial_Challenge_Mission_8_Completed", "operation": "==", "value": 1 }
                                                                    ] },
                  "values":     [ "achievement_2" ] }
            ]
        },

        {
            "sid": "Tutorial_Challenge_None_8",
            "state": "Hidden",

            "repeatable": true,
            "importanceType": "Side",

            "posX": -350.0, "posY": 150.0, "posZ": 0.0,

            "interactionActions": 
            [
                { "type":       "OpenMissionsPrologue",
                "values":     [ "Tutorial_Challenge_Mission_8" ] }
            ],

            "onDoneActions": 
            [
                { "type":       "SetCounterValue",
                "values":     [ "Tutorial_Challenge_Mission_8_Completed", "1" ] },

                { "type":       "SetAchievement",
                  "conditions": { "logicOperation": "And", "array": [ 
                                { "counterSid": "Tutorial_Challenge_Mission_1_Completed", "operation": "==", "value": 1 },
                                { "counterSid": "Tutorial_Challenge_Mission_2_Completed", "operation": "==", "value": 1 },
                                { "counterSid": "Tutorial_Challenge_Mission_3_Completed", "operation": "==", "value": 1 },
                                { "counterSid": "Tutorial_Challenge_Mission_4_Completed", "operation": "==", "value": 1 },
                                { "counterSid": "Tutorial_Challenge_Mission_5_Completed", "operation": "==", "value": 1 },
                                { "counterSid": "Tutorial_Challenge_Mission_6_Completed", "operation": "==", "value": 1 },
                                { "counterSid": "Tutorial_Challenge_Mission_7_Completed", "operation": "==", "value": 1 },
                                { "counterSid": "Tutorial_Challenge_Mission_8_Completed", "operation": "==", "value": 1 }
                                                                    ] },
                  "values":     [ "achievement_2" ] }
            ]
        }
    ]
}