{
	"array":
	[
		{
			"id": "druid",
			"mesh": "Nature/1Prefabs/druid",
			"mapMesh": "Nature/1Prefabs/druid_map",

			"scale": 1.475,
			"modelHeight": 0.68,
			"moveSpeed": 2.35,

			"attackTimeBefore": [ 0.59, 1.7, 0.6, 0.6, 0.6, 0.6 ],
			"attackTimeAfter": [ 1, 1, 1.6, 1, 1, 1 ],
			"rareIdleTime": 3.0,

			"takeDamageTime": 1.34,
			"deathTimeOffset": 3.2,

			"defaultAttacks":
			[
				{
					"animationIndex": 1
				}
			],

			"counterAttacks":
			[
				{
					"animationIndex": 0
				}
			],

			"alternativeAttacks":
			[
				{	
					"name": "common_attack_1_name",
					"abilityType": "Ability_type_attack_alt",
					"description": "common_attack_1_description",
					"additionalDescription": "",
					"animationIndex": 0,
					"useExpandTooltip": "false"
				}
			],

			"abilities":
			[
				{
					"name": "druid_ability_1_name",
					"abilityType": "Ability_type_special",
					"description": "druid_ability_1_description",
					"animationIndex": 4,
					"useExpandTooltip": "false"
				},
				{
					"name": "druid_ability_2_name",
					"abilityType": "Ability_type_debuff",
					"description": "druid_ability_2_description",
					"animationIndex": 3
				}
			],

			"baseClass":
                {
                    "name": "base_class_living",
                    "description": "base_class_living_description"
                },

			"passives":
			[
				{
					"name": "base_passive_remote_attack_name",
					"description": "base_passive_remote_attack_description"
				},
				{
					"name": "druid_passive_1_name",
					"description": "druid_passive_1_description"
				}
			]
		}
	]
}
