{
    "array": [
        {
            "id": "squad_demon_t3_t5_t6_1",
            "useOldSquads": false,
            "rollChance": 22,
            "canBeMainGuard": true,
            "baseSquad": {
                "units": [
                    {
                        "s": "wasp",
                        "v": 15016
                    },
                    {
                        "s": "godslayer_upg_alt",
                        "v": 15016
                    },
                    {
                        "s": "olgoi_upg_alt",
                        "v": 15016
                    }
                ]
            },
            "dynamicSquad": {
                "requiredValue": 15016,
                "units": [
                    "wasp",
                    "godslayer_upg_alt",
                    "olgoi_upg_alt"
                ]
            },
            "randomSquad": {
                "maxValue": 110016,
                "units": [
                    {
                        "s": "wasp",
                        "v": 110016
                    },
                    {
                        "s": "godslayer_upg_alt",
                        "v": 110016
                    },
                    {
                        "s": "olgoi_upg_alt",
                        "v": 110016
                    }
                ]
            },
            "tier": 6,
            "fraction": "demon"
        }
    ]
}