{
    "array": [
        {
            "id": "squad_unfrozen_t2_t4_t6_1",
            "useOldSquads": false,
            "rollChance": 19,
            "canBeMainGuard": true,
            "baseSquad": {
                "units": [
                    {
                        "s": "unfrozen_cultist_upg",
                        "v": 12186
                    },
                    {
                        "s": "eldritch_flyer_upg",
                        "v": 12186
                    },
                    {
                        "s": "arbitrator",
                        "v": 12186
                    }
                ]
            },
            "dynamicSquad": {
                "requiredValue": 12186,
                "units": [
                    "unfrozen_cultist_upg",
                    "eldritch_flyer_upg",
                    "arbitrator"
                ]
            },
            "randomSquad": {
                "maxValue": 85016,
                "units": [
                    {
                        "s": "unfrozen_cultist_upg",
                        "v": 85016
                    },
                    {
                        "s": "eldritch_flyer_upg",
                        "v": 85016
                    },
                    {
                        "s": "arbitrator",
                        "v": 85016
                    }
                ]
            },
            "tier": 6,
            "fraction": "unfrozen"
        }
    ]
}