{
    "array": [
        {
            "id": "squad_demon_t1_t3_t5_1",
            "useOldSquads": false,
            "rollChance": 12,
            "canBeMainGuard": true,
            "baseSquad": {
                "units": [
                    {
                        "s": "trick_demon_upg",
                        "v": 7015
                    },
                    {
                        "s": "wasp_upg",
                        "v": 7015
                    },
                    {
                        "s": "godslayer_upg_alt",
                        "v": 7015
                    }
                ]
            },
            "dynamicSquad": {
                "requiredValue": 7015,
                "units": [
                    "trick_demon_upg",
                    "wasp_upg",
                    "godslayer_upg_alt"
                ]
            },
            "randomSquad": {
                "maxValue": 53355,
                "units": [
                    {
                        "s": "trick_demon_upg",
                        "v": 53355
                    },
                    {
                        "s": "wasp_upg",
                        "v": 53355
                    },
                    {
                        "s": "godslayer_upg_alt",
                        "v": 53355
                    }
                ]
            },
            "tier": 5,
            "fraction": "demon"
        }
    ]
}